ascutil/__init__.py
ascutil/__init__.pyi
ascutil/ascutil.cpython-313-x86_64-linux-musl.so
ascutil/py.typed
ascutil-0.1.1.dist-info/METADATA
ascutil-0.1.1.dist-info/WHEEL
ascutil.libs/libgcc_s-f685abf1.so.1
ascutil-0.1.1.dist-info/RECORD
