Metadata-Version: 2.4
Name: ascutil
Version: 0.1.1
Classifier: Programming Language :: Rust
Classifier: Programming Language :: Python :: Implementation :: CPython
Classifier: Programming Language :: Python :: Implementation :: PyPy
Requires-Python: >=3.8
Project-URL: Homepage, https://github.com/heiljj/ascutil
